{
  "annotations": {
    "list": [
      {
        "builtIn": 1,
        "datasource": {
          "type": "grafana",
          "uid": "-- Grafana --"
        },
        "enable": true,
        "hide": true,
        "iconColor": "rgba(0, 211, 255, 1)",
        "name": "Annotations & Alerts",
        "type": "dashboard"
      }
    ]
  },
  "editable": true,
  "fiscalYearStartMonth": 0,
  "graphTooltip": 0,
  "id": 40,
  "links": [],
  "liveNow": false,
  "panels": [
    {
      "collapsed": false,
      "gridPos": {
        "h": 1,
        "w": 24,
        "x": 0,
        "y": 0
      },
      "id": 1,
      "panels": [],
      "title": "Cver Stage",
      "type": "row"
    },
    {
      "datasource": {
        "type": "prometheus",
        "uid": "prometheus"
      },
      "fieldConfig": {
        "defaults": {
          "color": {
            "mode": "thresholds"
          },
          "mappings": [],
          "thresholds": {
            "mode": "absolute",
            "steps": [
              {
                "color": "green",
                "value": null
              },
              {
                "color": "red",
                "value": 80
              }
            ]
          }
        },
        "overrides": []
      },
      "gridPos": {
        "h": 7,
        "w": 5,
        "x": 0,
        "y": 1
      },
      "id": 2,
      "options": {
        "colorMode": "value",
        "graphMode": "area",
        "justifyMode": "auto",
        "orientation": "auto",
        "reduceOptions": {
          "calcs": [
            "lastNotNull"
          ],
          "fields": "",
          "values": false
        },
        "textMode": "auto"
      },
      "pluginVersion": "9.5.3",
      "targets": [
        {
          "datasource": {
            "type": "prometheus",
            "uid": "prometheus"
          },
          "editorMode": "code",
          "expr": "sum(kube_pod_status_ready{namespace=\"cver-stage\"})",
          "legendFormat": "__auto",
          "range": true,
          "refId": "A"
        }
      ],
      "title": "Stage Pod Count",
      "type": "stat"
    },
    {
      "aliasColors": {},
      "bars": false,
      "dashLength": 10,
      "dashes": false,
      "datasource": {
        "type": "prometheus",
        "uid": "prometheus"
      },
      "fill": 10,
      "fillGradient": 0,
      "gridPos": {
        "h": 7,
        "w": 13,
        "x": 11,
        "y": 1
      },
      "hiddenSeries": false,
      "id": 7,
      "interval": "1m",
      "legend": {
        "alignAsTable": true,
        "avg": false,
        "current": false,
        "max": false,
        "min": false,
        "rightSide": true,
        "show": true,
        "total": false,
        "values": false
      },
      "lines": true,
      "linewidth": 0,
      "links": [],
      "nullPointMode": "null as zero",
      "options": {
        "alertThreshold": true
      },
      "percentage": false,
      "pluginVersion": "9.5.3",
      "pointradius": 5,
      "points": false,
      "renderer": "flot",
      "seriesOverrides": [
        {
          "alias": "quota - requests",
          "color": "#F2495C",
          "dashes": true,
          "fill": 0,
          "hiddenSeries": true,
          "hideTooltip": true,
          "legend": true,
          "linewidth": 2,
          "stack": false
        },
        {
          "alias": "quota - limits",
          "color": "#FF9830",
          "dashes": true,
          "fill": 0,
          "hiddenSeries": true,
          "hideTooltip": true,
          "legend": true,
          "linewidth": 2,
          "stack": false
        }
      ],
      "spaceLength": 10,
      "stack": true,
      "steppedLine": false,
      "targets": [
        {
          "datasource": {
            "uid": "$datasource"
          },
          "editorMode": "code",
          "expr": "sum(node_namespace_pod_container:container_cpu_usage_seconds_total:sum_irate{namespace=\"cver-stage\"}) by (pod)",
          "format": "time_series",
          "intervalFactor": 2,
          "legendFormat": "{{pod}}",
          "range": true,
          "refId": "A",
          "step": 10
        },
        {
          "datasource": {
            "uid": "$datasource"
          },
          "editorMode": "code",
          "expr": "scalar(kube_resourcequota{namespace=\"cver-stage\", type=\"hard\",resource=\"requests.cpu\"})",
          "format": "time_series",
          "intervalFactor": 2,
          "legendFormat": "quota - requests",
          "range": true,
          "refId": "B",
          "step": 10
        },
        {
          "datasource": {
            "uid": "$datasource"
          },
          "editorMode": "code",
          "expr": "scalar(kube_resourcequota{namespace=\"cver-stage\", type=\"hard\",resource=\"limits.cpu\"})",
          "format": "time_series",
          "intervalFactor": 2,
          "legendFormat": "quota - limits",
          "range": true,
          "refId": "C",
          "step": 10
        }
      ],
      "thresholds": [],
      "timeRegions": [],
      "title": "CPU Usage",
      "tooltip": {
        "shared": false,
        "sort": 2,
        "value_type": "individual"
      },
      "type": "graph",
      "xaxis": {
        "mode": "time",
        "show": true,
        "values": []
      },
      "yaxes": [
        {
          "format": "short",
          "logBase": 1,
          "min": 0,
          "show": true
        },
        {
          "format": "short",
          "logBase": 1,
          "show": false
        }
      ],
      "yaxis": {
        "align": false
      }
    },
    {
      "aliasColors": {},
      "bars": false,
      "dashLength": 10,
      "dashes": false,
      "datasource": {
        "type": "prometheus",
        "uid": "prometheus"
      },
      "fill": 10,
      "fillGradient": 0,
      "gridPos": {
        "h": 8,
        "w": 13,
        "x": 11,
        "y": 8
      },
      "hiddenSeries": false,
      "id": 3,
      "interval": "1m",
      "legend": {
        "alignAsTable": true,
        "avg": false,
        "current": false,
        "max": false,
        "min": false,
        "rightSide": true,
        "show": true,
        "total": false,
        "values": false
      },
      "lines": true,
      "linewidth": 0,
      "links": [],
      "nullPointMode": "null as zero",
      "options": {
        "alertThreshold": true
      },
      "percentage": false,
      "pluginVersion": "9.5.3",
      "pointradius": 5,
      "points": false,
      "renderer": "flot",
      "seriesOverrides": [
        {
          "alias": "quota - requests",
          "color": "#F2495C",
          "dashes": true,
          "fill": 0,
          "hiddenSeries": true,
          "hideTooltip": true,
          "legend": true,
          "linewidth": 2,
          "stack": false
        },
        {
          "alias": "quota - limits",
          "color": "#FF9830",
          "dashes": true,
          "fill": 0,
          "hiddenSeries": true,
          "hideTooltip": true,
          "legend": true,
          "linewidth": 2,
          "stack": false
        }
      ],
      "spaceLength": 10,
      "stack": true,
      "steppedLine": false,
      "targets": [
        {
          "datasource": {
            "uid": "$datasource"
          },
          "editorMode": "code",
          "expr": "sum(container_memory_working_set_bytes{job=\"kubelet\", metrics_path=\"/metrics/cadvisor\", namespace=\"cver-stage\", container!=\"\", image!=\"\"}) by (pod)",
          "format": "time_series",
          "intervalFactor": 2,
          "legendFormat": "{{pod}}",
          "range": true,
          "refId": "A",
          "step": 10
        },
        {
          "datasource": {
            "uid": "$datasource"
          },
          "editorMode": "code",
          "expr": "scalar(kube_resourcequota{namespace=\"cver-stage\", type=\"hard\",resource=\"requests.memory\"})",
          "format": "time_series",
          "intervalFactor": 2,
          "legendFormat": "quota - requests",
          "range": true,
          "refId": "B",
          "step": 10
        },
        {
          "datasource": {
            "uid": "$datasource"
          },
          "editorMode": "code",
          "expr": "scalar(kube_resourcequota{namespace=\"cver-stage\", type=\"hard\",resource=\"limits.memory\"})",
          "format": "time_series",
          "intervalFactor": 2,
          "legendFormat": "quota - limits",
          "range": true,
          "refId": "C",
          "step": 10
        }
      ],
      "thresholds": [],
      "timeRegions": [],
      "title": "Memory Usage (w/o cache)",
      "tooltip": {
        "shared": false,
        "sort": 2,
        "value_type": "individual"
      },
      "type": "graph",
      "xaxis": {
        "mode": "time",
        "show": true,
        "values": []
      },
      "yaxes": [
        {
          "format": "bytes",
          "logBase": 1,
          "min": 0,
          "show": true
        },
        {
          "format": "short",
          "logBase": 1,
          "show": false
        }
      ],
      "yaxis": {
        "align": false
      }
    },
    {
      "collapsed": false,
      "gridPos": {
        "h": 1,
        "w": 24,
        "x": 0,
        "y": 16
      },
      "id": 4,
      "panels": [],
      "title": "Cver Test",
      "type": "row"
    },
    {
      "datasource": {
        "type": "prometheus",
        "uid": "prometheus"
      },
      "fieldConfig": {
        "defaults": {
          "color": {
            "mode": "thresholds"
          },
          "mappings": [],
          "thresholds": {
            "mode": "absolute",
            "steps": [
              {
                "color": "green",
                "value": null
              },
              {
                "color": "red",
                "value": 80
              }
            ]
          }
        },
        "overrides": []
      },
      "gridPos": {
        "h": 7,
        "w": 5,
        "x": 0,
        "y": 17
      },
      "id": 5,
      "options": {
        "colorMode": "value",
        "graphMode": "area",
        "justifyMode": "auto",
        "orientation": "auto",
        "reduceOptions": {
          "calcs": [
            "lastNotNull"
          ],
          "fields": "",
          "values": false
        },
        "textMode": "auto"
      },
      "pluginVersion": "9.5.3",
      "targets": [
        {
          "datasource": {
            "type": "prometheus",
            "uid": "prometheus"
          },
          "editorMode": "code",
          "expr": "sum(kube_pod_status_ready{namespace=\"cver-test\"})",
          "legendFormat": "__auto",
          "range": true,
          "refId": "A"
        }
      ],
      "title": "Test Pod Count",
      "type": "stat"
    },
    {
      "aliasColors": {},
      "bars": false,
      "dashLength": 10,
      "dashes": false,
      "datasource": {
        "type": "prometheus",
        "uid": "prometheus"
      },
      "fill": 10,
      "fillGradient": 0,
      "gridPos": {
        "h": 8,
        "w": 13,
        "x": 11,
        "y": 17
      },
      "hiddenSeries": false,
      "id": 6,
      "interval": "1m",
      "legend": {
        "alignAsTable": true,
        "avg": false,
        "current": false,
        "max": false,
        "min": false,
        "rightSide": true,
        "show": true,
        "total": false,
        "values": false
      },
      "lines": true,
      "linewidth": 0,
      "links": [],
      "nullPointMode": "null as zero",
      "options": {
        "alertThreshold": true
      },
      "percentage": false,
      "pluginVersion": "9.5.3",
      "pointradius": 5,
      "points": false,
      "renderer": "flot",
      "seriesOverrides": [
        {
          "alias": "quota - requests",
          "color": "#F2495C",
          "dashes": true,
          "fill": 0,
          "hiddenSeries": true,
          "hideTooltip": true,
          "legend": true,
          "linewidth": 2,
          "stack": false
        },
        {
          "alias": "quota - limits",
          "color": "#FF9830",
          "dashes": true,
          "fill": 0,
          "hiddenSeries": true,
          "hideTooltip": true,
          "legend": true,
          "linewidth": 2,
          "stack": false
        }
      ],
      "spaceLength": 10,
      "stack": true,
      "steppedLine": false,
      "targets": [
        {
          "datasource": {
            "uid": "$datasource"
          },
          "editorMode": "code",
          "expr": "sum(container_memory_working_set_bytes{job=\"kubelet\", metrics_path=\"/metrics/cadvisor\", namespace=\"cver-test\", container!=\"\", image!=\"\"}) by (pod)",
          "format": "time_series",
          "intervalFactor": 2,
          "legendFormat": "{{pod}}",
          "range": true,
          "refId": "A",
          "step": 10
        },
        {
          "datasource": {
            "uid": "$datasource"
          },
          "editorMode": "code",
          "expr": "scalar(kube_resourcequota{namespace=\"cver-test\", type=\"hard\",resource=\"requests.memory\"})",
          "format": "time_series",
          "intervalFactor": 2,
          "legendFormat": "quota - requests",
          "range": true,
          "refId": "B",
          "step": 10
        },
        {
          "datasource": {
            "uid": "$datasource"
          },
          "editorMode": "code",
          "expr": "scalar(kube_resourcequota{namespace=\"cver-test\", type=\"hard\",resource=\"limits.memory\"})",
          "format": "time_series",
          "intervalFactor": 2,
          "legendFormat": "quota - limits",
          "range": true,
          "refId": "C",
          "step": 10
        }
      ],
      "thresholds": [],
      "timeRegions": [],
      "title": "Memory Usage (w/o cache)",
      "tooltip": {
        "shared": false,
        "sort": 2,
        "value_type": "individual"
      },
      "type": "graph",
      "xaxis": {
        "mode": "time",
        "show": true,
        "values": []
      },
      "yaxes": [
        {
          "format": "bytes",
          "logBase": 1,
          "min": 0,
          "show": true
        },
        {
          "format": "short",
          "logBase": 1,
          "show": false
        }
      ],
      "yaxis": {
        "align": false
      }
    }
  ],
  "refresh": "",
  "schemaVersion": 38,
  "style": "dark",
  "tags": [],
  "templating": {
    "list": []
  },
  "time": {
    "from": "now-30m",
    "to": "now"
  },
  "timepicker": {},
  "timezone": "",
  "title": "Cver-New",
  "uid": "b5665f5c-87a3-4a88-a8b8-022e80f9c9e3",
  "version": 1,
  "weekStart": ""
}